mocks_db/__init__.py
mocks_db/generator.py
mocks_db/main.py
mocks_db/schema.py
mocks_db/server.py
mocks_db-0.1.0.dist-info/licenses/LICENSE
mocks_db-0.1.0.dist-info/METADATA
mocks_db-0.1.0.dist-info/WHEEL
mocks_db-0.1.0.dist-info/entry_points.txt
mocks_db-0.1.0.dist-info/top_level.txt
mocks_db-0.1.0.dist-info/RECORD
