Metadata-Version: 2.4
Name: mocks-db
Version: 0.1.0
Summary: A mock MySQL server that generates junk data based on your schema.
Author-email: Pratyush <pratyush@example.com>
License: MIT License
Project-URL: Homepage, https://github.com/pratyush/mocks-db
Project-URL: Bug Tracker, https://github.com/pratyush/mocks-db/issues
Classifier: Programming Language :: Python :: 3
Classifier: License :: OSI Approved :: MIT License
Classifier: Operating System :: OS Independent
Requires-Python: >=3.9
License-File: LICENSE
Requires-Dist: mysql-mimic>=2.3.0
Requires-Dist: faker>=23.0.0
Requires-Dist: click>=8.1.0
Requires-Dist: sqlglot>=20.0.0
Provides-Extra: dev
Requires-Dist: pytest; extra == "dev"
Requires-Dist: pytest-asyncio; extra == "dev"
Requires-Dist: flake8; extra == "dev"
Requires-Dist: build; extra == "dev"
Requires-Dist: twine; extra == "dev"
Dynamic: license-file
